{
 "cells": [
  {
   "cell_type": "markdown",
   "id": "0aaa6b4e",
   "metadata": {},
   "source": [
    "### 阶段1：基于生成器的协程（Python 2.5+）"
   ]
  },
  {
   "cell_type": "code",
   "execution_count": 1,
   "id": "b0869bb1",
   "metadata": {},
   "outputs": [
    {
     "name": "stdout",
     "output_type": "stream",
     "text": [
      "1\n",
      "2\n",
      "13\n"
     ]
    },
    {
     "ename": "StopIteration",
     "evalue": "",
     "output_type": "error",
     "traceback": [
      "\u001b[31m---------------------------------------------------------------------------\u001b[39m",
      "\u001b[31mStopIteration\u001b[39m                             Traceback (most recent call last)",
      "\u001b[36mCell\u001b[39m\u001b[36m \u001b[39m\u001b[32mIn[1]\u001b[39m\u001b[32m, line 10\u001b[39m\n\u001b[32m      8\u001b[39m \u001b[38;5;28mprint\u001b[39m(gen.send(\u001b[32m10\u001b[39m))  \u001b[38;5;66;03m# 2\u001b[39;00m\n\u001b[32m      9\u001b[39m \u001b[38;5;28mprint\u001b[39m(gen.send(\u001b[32m10\u001b[39m))  \u001b[38;5;66;03m# 13\u001b[39;00m\n\u001b[32m---> \u001b[39m\u001b[32m10\u001b[39m \u001b[38;5;28mprint\u001b[39m(\u001b[38;5;28;43mnext\u001b[39;49m\u001b[43m(\u001b[49m\u001b[43mgen\u001b[49m\u001b[43m)\u001b[49m)  \u001b[38;5;66;03m# StopIteration\u001b[39;00m\n",
      "\u001b[31mStopIteration\u001b[39m: "
     ]
    }
   ],
   "source": [
    "def simple_generator():\n",
    "    yield 1\n",
    "    x = yield 2  \n",
    "    yield x + 3\n",
    "\n",
    "gen = simple_generator()\n",
    "print(next(gen))  # 1\n",
    "print(gen.send(10))  # 2\n",
    "print(gen.send(10))  # 13\n",
    "print(next(gen))  # StopIteration"
   ]
  },
  {
   "cell_type": "markdown",
   "id": "b8b97ea1",
   "metadata": {},
   "source": [
    "### 阶段2：@asyncio.coroutine装饰器（Python 3.4）"
   ]
  },
  {
   "cell_type": "code",
   "execution_count": null,
   "id": "8ef739f4",
   "metadata": {},
   "outputs": [
    {
     "ename": "AttributeError",
     "evalue": "module 'asyncio' has no attribute 'coroutine'",
     "output_type": "error",
     "traceback": [
      "\u001b[31m---------------------------------------------------------------------------\u001b[39m",
      "\u001b[31mAttributeError\u001b[39m                            Traceback (most recent call last)",
      "\u001b[36mCell\u001b[39m\u001b[36m \u001b[39m\u001b[32mIn[2]\u001b[39m\u001b[32m, line 4\u001b[39m\n\u001b[32m      1\u001b[39m \u001b[38;5;28;01mimport\u001b[39;00m\u001b[38;5;250m \u001b[39m\u001b[34;01masyncio\u001b[39;00m\n\u001b[32m      3\u001b[39m \u001b[38;5;66;03m# 协程雏形 (Python 3.4)\u001b[39;00m\n\u001b[32m----> \u001b[39m\u001b[32m4\u001b[39m \u001b[38;5;129m@asyncio\u001b[39m\u001b[43m.\u001b[49m\u001b[43mcoroutine\u001b[49m\n\u001b[32m      5\u001b[39m \u001b[38;5;28;01mdef\u001b[39;00m\u001b[38;5;250m \u001b[39m\u001b[34mold_style_coro\u001b[39m():\n\u001b[32m      6\u001b[39m     \u001b[38;5;28mprint\u001b[39m(\u001b[33m\"\u001b[39m\u001b[33mStart\u001b[39m\u001b[33m\"\u001b[39m)\n\u001b[32m      7\u001b[39m     \u001b[38;5;28;01myield from\u001b[39;00m asyncio.sleep(\u001b[32m1\u001b[39m)  \u001b[38;5;66;03m# 委托给另一个生成器\u001b[39;00m\n",
      "\u001b[31mAttributeError\u001b[39m: module 'asyncio' has no attribute 'coroutine'"
     ]
    }
   ],
   "source": [
    "import asyncio\n",
    "\n",
    "# 协程雏形 (Python 3.4) ，在Python 3.12中，@asyncio.coroutine装饰器已被移除\n",
    "@asyncio.coroutine\n",
    "def old_style_coro():\n",
    "    print(\"Start\")\n",
    "    yield from asyncio.sleep(1)  # 委托给另一个生成器\n",
    "    print(\"End\")\n",
    "\n",
    "# 等价于：\n",
    "def old_style_coro_expanded():\n",
    "    print(\"Start\")\n",
    "    # yield from展开为显式循环\n",
    "    sleep_gen = asyncio.sleep(1)\n",
    "    try:\n",
    "        while True:\n",
    "            value = next(sleep_gen)\n",
    "            try:\n",
    "                yielded_value = yield value\n",
    "            except Exception as e:\n",
    "                sleep_gen.throw(e)\n",
    "            else:\n",
    "                sleep_gen.send(yielded_value)\n",
    "    except StopIteration:\n",
    "        pass\n",
    "    print(\"End\")"
   ]
  },
  {
   "cell_type": "markdown",
   "id": "47507d7d",
   "metadata": {},
   "source": [
    "### 阶段3：原生协程（Python 3.5+）"
   ]
  },
  {
   "cell_type": "code",
   "execution_count": 3,
   "id": "c4a61505",
   "metadata": {},
   "outputs": [
    {
     "name": "stdout",
     "output_type": "stream",
     "text": [
      "  1           0 RETURN_GENERATOR\n",
      "              2 POP_TOP\n",
      "              4 RESUME                   0\n",
      "\n",
      "  2           6 LOAD_GLOBAL              1 (NULL + print)\n",
      "             16 LOAD_CONST               1 ('Start')\n",
      "             18 CALL                     1\n",
      "             26 POP_TOP\n",
      "\n",
      "  3          28 LOAD_GLOBAL              2 (asyncio)\n",
      "             38 LOAD_ATTR                5 (NULL|self + sleep)\n",
      "             58 LOAD_CONST               2 (1)\n",
      "             60 CALL                     1\n",
      "             68 GET_AWAITABLE            0\n",
      "             70 LOAD_CONST               0 (None)\n",
      "        >>   72 SEND                     3 (to 82)\n",
      "             76 YIELD_VALUE              2\n",
      "             78 RESUME                   3\n",
      "             80 JUMP_BACKWARD_NO_INTERRUPT     5 (to 72)\n",
      "        >>   82 END_SEND\n",
      "             84 POP_TOP\n",
      "\n",
      "  4          86 LOAD_GLOBAL              1 (NULL + print)\n",
      "             96 LOAD_CONST               3 ('End')\n",
      "             98 CALL                     1\n",
      "            106 POP_TOP\n",
      "            108 RETURN_CONST             0 (None)\n",
      "\n",
      "  3     >>  110 CLEANUP_THROW\n",
      "            112 JUMP_BACKWARD           16 (to 82)\n",
      "        >>  114 CALL_INTRINSIC_1         3 (INTRINSIC_STOPITERATION_ERROR)\n",
      "            116 RERAISE                  1\n",
      "ExceptionTable:\n",
      "  4 to 74 -> 114 [0] lasti\n",
      "  76 to 76 -> 110 [2]\n",
      "  78 to 110 -> 114 [0] lasti\n"
     ]
    }
   ],
   "source": [
    "async def native_coro():\n",
    "    print(\"Start\")\n",
    "    await asyncio.sleep(1)  # 语法糖替代 yield from\n",
    "    print(\"End\")\n",
    "\n",
    "# 反编译查看字节码差异\n",
    "import dis\n",
    "dis.dis(native_coro)"
   ]
  }
 ],
 "metadata": {
  "kernelspec": {
   "display_name": "MLOps",
   "language": "python",
   "name": "python3"
  },
  "language_info": {
   "codemirror_mode": {
    "name": "ipython",
    "version": 3
   },
   "file_extension": ".py",
   "mimetype": "text/x-python",
   "name": "python",
   "nbconvert_exporter": "python",
   "pygments_lexer": "ipython3",
   "version": "3.12.11"
  }
 },
 "nbformat": 4,
 "nbformat_minor": 5
}
